{
 "department": "內科、外科、兒科、精神科、婦產科",
 "subject": "專科護理通論",
 "1": "C",
 "2": "C",
 "3": "B",
 "4": "A",
 "5": "A",
 "6": "A",
 "7": "A",
 "8": "A",
 "9": "C",
 "10": "B",
 "11": "D",
 "12": "A",
 "13": "C",
 "14": "A",
 "15": "A",
 "16": "A",
 "17": "C",
 "18": "D",
 "19": "D",
 "20": "C",
 "21": "C",
 "22": "C",
 "23": "B",
 "24": "C",
 "25": "C",
 "26": "B",
 "27": "A",
 "28": "A",
 "29": "B",
 "30": "C",
 "31": "B",
 "32": "C",
 "33": "A",
 "34": "D",
 "35": "C",
 "36": "C",
 "37": "B",
 "38": "B",
 "39": "D",
 "40": "A",
 "41": "B",
 "42": "B",
 "43": "A",
 "44": "D",
 "45": "C",
 "46": "送分",
 "47": "D",
 "48": "B",
 "49": "D",
 "50": "B",
 "51": "C",
 "52": "D",
 "53": "B",
 "54": "D",
 "55": "B",
 "56": "B",
 "57": "D",
 "58": "D",
 "59": "A",
 "60": "D",
 "61": "B",
 "62": "D",
 "63": "B",
 "64": "D",
 "65": "A",
 "66": "C",
 "67": "B",
 "68": "D",
 "69": "D",
 "70": "B",
 "71": "B",
 "72": "A",
 "73": "A",
 "74": "D",
 "75": "A",
 "76": "B",
 "77": "D",
 "78": "B",
 "79": "A",
 "80": "C"
}